CIDER/__init__.py
CIDER/cider.py
cider_chem-0.0.1.dev0.dist-info/LICENSE
cider_chem-0.0.1.dev0.dist-info/METADATA
cider_chem-0.0.1.dev0.dist-info/WHEEL
cider_chem-0.0.1.dev0.dist-info/top_level.txt
cider_chem-0.0.1.dev0.dist-info/RECORD
