Metadata-Version: 2.1
Name: cider-chem
Version: 0.0.1.dev0
Summary: ChemIcal DatasEt compaRator (CIDER) is a Python package which primarily utilizes RDKit to compare and visualize different chemical compounds from two different datasets.
Home-page: https://github.com/hannbus/ChemIcal_DatasEt_compaRator
Author: Hannah Busch
Author-email: hannah.busch@uni-jena.de
Maintainer: Jonas Schaub, Otto Brinkhaus, Kohulan Rajan
Maintainer-email: jonas.schaub@uni-jena.de, henning.brinkhaus@uni-jena.de, kohulan.rajan@uni-jena.de
License: MIT
Platform: UNKNOWN
Classifier: Programming Language :: Python :: 3
Classifier: Programming Language :: Python :: 3.5
Classifier: Programming Language :: Python :: 3.6
Classifier: Programming Language :: Python :: 3.7
Classifier: Programming Language :: Python :: 3.8
Classifier: Programming Language :: Python :: 3 :: Only
Classifier: License :: OSI Approved :: MIT License
Classifier: Operating System :: OS Independent
Requires-Python: >=3.5
License-File: LICENSE
Requires-Dist: FPDF (==1.7.2)
Requires-Dist: chemplot (==1.2.0)
Requires-Dist: matplotlib (==3.5.1)
Requires-Dist: matplotlib-venn (==0.11.6)
Requires-Dist: notebook
Requires-Dist: rdkit-pypi
Requires-Dist: seaborn (==0.11.2)
